CHANGES.txt
MANIFEST.in
README.txt
setup.cfg
setup.py
wsapi4plone/__init__.py
wsapi4plone.client.egg-info/PKG-INFO
wsapi4plone.client.egg-info/SOURCES.txt
wsapi4plone.client.egg-info/dependency_links.txt
wsapi4plone.client.egg-info/entry_points.txt
wsapi4plone.client.egg-info/namespace_packages.txt
wsapi4plone.client.egg-info/not-zip-safe
wsapi4plone.client.egg-info/requires.txt
wsapi4plone.client.egg-info/top_level.txt
wsapi4plone/client/__init__.py