Metadata-Version: 1.0
Name: wsapi4plone.client
Version: 0.1a3
Summary: An XML-RPC client specially created for interfacing with a Plone site using the Web Services API for Plone (wsapi4plone).
Home-page: https://weblion.psu.edu/trac/weblion/wiki/WebServicesApiPlone
Author: WebLion Group, Penn State University
Author-email: support@weblion.psu.edu
License: GPL
Keywords: wsapi,api,xmlrpc,weblion
Platform: UNKNOWN
Classifier: Framework :: Plone
Classifier: Framework :: Zope2
Classifier: Programming Language :: Python
Classifier: Programming Language :: Python :: 2.4
Classifier: Topic :: Software Development :: Libraries :: Python Modules
Classifier: Intended Audience :: Developers
Classifier: Development Status :: 3 - Alpha
